wiseman_library/__init__.py
wiseman_library/Lissener.py
wiseman_library/Recognizer.py
wiseman_library/Recorder.py
wiseman_library/speaker.py
wiseman_library-1.2.1.dist-info/LICENSE
wiseman_library-1.2.1.dist-info/METADATA
wiseman_library-1.2.1.dist-info/WHEEL
wiseman_library-1.2.1.dist-info/RECORD
