Metadata-Version: 2.1
Name: wiseman_library
Version: 1.2.1
Summary: wiseman bundles the voice assistant infrastructure into a python library
Home-page: https://github.com/adem-ocel/wiseman-library
License: MIT
Keywords: voice assistant,wiseman,library
Author: Adem
Author-email: adem@example.com
Requires-Python: >=3.12,<4.0
Classifier: License :: OSI Approved :: MIT License
Classifier: Programming Language :: Python :: 3
Classifier: Programming Language :: Python :: 3.12
Project-URL: Repository, https://github.com/adem-ocel/wiseman-library
